eventdbx/__init__.py
eventdbx/client.py
eventdbx/control_schema.py
eventdbx/noise.py
eventdbx/py.typed
eventdbx/proto/__init__.py
eventdbx/proto/control.capnp
eventdbx-0.1.4.dist-info/METADATA
eventdbx-0.1.4.dist-info/WHEEL
eventdbx-0.1.4.dist-info/licenses/LICENSE
eventdbx-0.1.4.dist-info/RECORD
