Metadata-Version: 2.4
Name: eventdbx
Version: 0.1.4
Summary: Official (preview) Python client for the EventDBX ingestion API.
Project-URL: Homepage, https://eventdbx.com
Project-URL: Repository, https://github.com/eventdbx/eventdbx-python
Project-URL: Bug Tracker, https://github.com/eventdbx/eventdbx-python/issues
Project-URL: Documentation, https://docs.eventdbx.com
Author-email: Patrick Thach <thachp@gmail.com>
License: MIT License
License-File: LICENSE
Keywords: analytics,client,eventdbx,events,sdk
Classifier: Development Status :: 3 - Alpha
Classifier: Intended Audience :: Developers
Classifier: License :: OSI Approved :: MIT License
Classifier: Programming Language :: Python
Classifier: Programming Language :: Python :: 3
Classifier: Programming Language :: Python :: 3.9
Classifier: Programming Language :: Python :: 3.10
Classifier: Programming Language :: Python :: 3.11
Classifier: Programming Language :: Python :: 3.12
Classifier: Topic :: Software Development :: Libraries :: Application Frameworks
Requires-Python: >=3.9
Requires-Dist: httpx<0.29,>=0.27
Requires-Dist: noiseprotocol<0.4,>=0.3
Requires-Dist: pycapnp<3,>=1.3
Provides-Extra: dev
Requires-Dist: build>=1.2; extra == 'dev'
Requires-Dist: pytest-cov>=5; extra == 'dev'
Requires-Dist: pytest>=8.2; extra == 'dev'
Requires-Dist: twine>=5.1; extra == 'dev'
